milan/__init__.py
milan/browser.py
milan/chromium.py
milan/errors.py
milan/executables.py
milan/firefox.py
milan/video_recorder.py
milan/webkit.py
milan/browser_extensions/__init__.py
milan/browser_extensions/chromium/milan/background.js
milan/browser_extensions/chromium/milan/manifest.json
milan/cdp/__init__.py
milan/cdp/websocket_browser.py
milan/cdp/websocket_client.py
milan/cli/__init__.py
milan/cli/background_init.py
milan/cli/cli.py
milan/cli/entry_points.py
milan/cli/run.py
milan/contrib/__init__.py
milan/contrib/lona.py
milan/frontend/__init__.py
milan/frontend/commands.py
milan/frontend/proxy.py
milan/frontend/server.py
milan/frontend/static/address-bar.js
milan/frontend/static/cursor.js
milan/frontend/static/frontend.js
milan/frontend/static/index.html
milan/frontend/static/milan.css
milan/frontend/static/assets/cursor.svg
"milan/frontend/static/assets/fonts/google-material-design-icons/MaterialSymbolsOutlined[FILL,GRAD,opsz,wght].codepoints"
"milan/frontend/static/assets/fonts/google-material-design-icons/MaterialSymbolsOutlined[FILL,GRAD,opsz,wght].ttf"
"milan/frontend/static/assets/fonts/google-material-design-icons/MaterialSymbolsOutlined[FILL,GRAD,opsz,wght].woff2"
"milan/frontend/static/assets/fonts/google-material-design-icons/MaterialSymbolsRounded[FILL,GRAD,opsz,wght].codepoints"
"milan/frontend/static/assets/fonts/google-material-design-icons/MaterialSymbolsRounded[FILL,GRAD,opsz,wght].ttf"
"milan/frontend/static/assets/fonts/google-material-design-icons/MaterialSymbolsRounded[FILL,GRAD,opsz,wght].woff2"
"milan/frontend/static/assets/fonts/google-material-design-icons/MaterialSymbolsSharp[FILL,GRAD,opsz,wght].codepoints"
"milan/frontend/static/assets/fonts/google-material-design-icons/MaterialSymbolsSharp[FILL,GRAD,opsz,wght].ttf"
"milan/frontend/static/assets/fonts/google-material-design-icons/MaterialSymbolsSharp[FILL,GRAD,opsz,wght].woff2"
milan/frontend/static/assets/fonts/google-material-design-icons/README.txt
milan-0.1.4.dist-info/LICENSE.txt
milan-0.1.4.dist-info/METADATA
milan-0.1.4.dist-info/WHEEL
milan-0.1.4.dist-info/top_level.txt
milan-0.1.4.dist-info/RECORD
