Metadata-Version: 2.1
Name: milan
Version: 0.1.4
Summary: Browser testing and capturing tool
Author-email: Florian Scherf <mail@florianscherf.de>
License: MIT License
Classifier: Development Status :: 4 - Beta
Classifier: Environment :: Web Environment
Classifier: Intended Audience :: Developers
Classifier: License :: OSI Approved :: MIT License
Classifier: Operating System :: Unix
Classifier: Programming Language :: JavaScript
Classifier: Programming Language :: Python :: 3 :: Only
Classifier: Topic :: Documentation
Classifier: Topic :: Internet
Classifier: Topic :: Internet :: WWW/HTTP
Classifier: Topic :: Internet :: WWW/HTTP :: Browsers
Classifier: Topic :: Multimedia :: Video
Classifier: Topic :: Multimedia :: Video :: Capture
Classifier: Topic :: Software Development
Classifier: Topic :: Software Development :: Documentation
Classifier: Topic :: Software Development :: Testing
Classifier: Topic :: Software Development :: User Interfaces
Requires-Python: >=3.8
License-File: LICENSE.txt
Requires-Dist: playwright <1.46,>=1.44
Requires-Dist: aiohttp ~=3.9.0
Requires-Dist: urllib3
Requires-Dist: simple-logging-setup
Requires-Dist: rlpython
Provides-Extra: dev
Requires-Dist: build ; extra == 'dev'
Requires-Dist: twine ; extra == 'dev'
Requires-Dist: tox ; extra == 'dev'
Requires-Dist: simple-logging-setup ; extra == 'dev'
Requires-Dist: debugpy ; extra == 'dev'
Requires-Dist: mkdocs ==1.6.0 ; extra == 'dev'
Requires-Dist: mkdocstrings[python] ==0.25.1 ; extra == 'dev'
Requires-Dist: mkdocs-material ==9.5.29 ; extra == 'dev'
Provides-Extra: docker
Requires-Dist: tox ==4.16.0 ; extra == 'docker'
Provides-Extra: test
Requires-Dist: coverage ==7.6.0 ; extra == 'test'
Requires-Dist: pytest ==8.3.1 ; extra == 'test'
Requires-Dist: pytest-timeout ==2.3.1 ; extra == 'test'
Requires-Dist: pytest-asyncio ==0.23.8 ; extra == 'test'
Requires-Dist: lona ==1.16.2 ; extra == 'test'
Requires-Dist: lona-picocss ==0.4.3 ; extra == 'test'
